nos/__init__.py
nos/constants.py
nos/exceptions.py
nos/logging.py
nos/protoc.py
nos/telemetry.py
nos/version.py
nos/catalogs/model_profile_catalog.json
nos/cli/cli.py
nos/cli/hub.py
nos/cli/predict.py
nos/cli/profile.py
nos/cli/serve.py
nos/cli/system.py
nos/cli/utils.py
nos/cli/templates/docker-compose.serve.yml.j2
nos/client/__init__.py
nos/client/grpc.py
nos/common/__init__.py
nos/common/cloudpickle.py
nos/common/exceptions.py
nos/common/git.py
nos/common/helpers.py
nos/common/metaclass.py
nos/common/profiler.py
nos/common/runtime.py
nos/common/shm.py
nos/common/spec.py
nos/common/system.py
nos/common/tasks.py
nos/common/types.py
nos/common/io/__init__.py
nos/common/io/video/base.py
nos/common/io/video/opencv.py
nos/executors/__init__.py
nos/executors/ray.py
nos/hub/__init__.py
nos/hub/config.py
nos/hub/hf.py
nos/managers/__init__.py
nos/managers/model.py
nos/managers/pool.py
nos/models/__init__.py
nos/models/_noop.py
nos/models/blip.py
nos/models/clip.py
nos/models/faster_rcnn.py
nos/models/llm.py
nos/models/monodepth.py
nos/models/owlvit.py
nos/models/sam.py
nos/models/stable_diffusion.py
nos/models/tts.py
nos/models/whisper.py
nos/models/yolox.py
nos/models/dreambooth/dreambooth.py
nos/models/dreambooth/hub.py
nos/models/openmmlab/hub.py
nos/models/openmmlab/mmdetection.py
nos/models/super_resolution/__init__.py
nos/models/super_resolution/config.py
nos/models/super_resolution/ldm.py
nos/models/super_resolution/swin2sr.py
nos/neuron/device.py
nos/proto/nos_service.proto
nos/server/__init__.py
nos/server/_docker.py
nos/server/_runtime.py
nos/server/_service.py
nos/server/http/_exceptions.py
nos/server/http/_security.py
nos/server/http/_service.py
nos/server/http/_utils.py
nos/server/http/integrations/openai/models.py
nos/test/benchmark.py
nos/test/conftest.py
nos/test/utils.py
nos/test/test_data/test.jpg
nos/test/test_data/test.mp4
nos/test/test_data/test_speech.flac
nos/test/test_data/hub/custom_model/models/model.py
torch_nos-0.3.0.dist-info/LICENSE
torch_nos-0.3.0.dist-info/METADATA
torch_nos-0.3.0.dist-info/WHEEL
torch_nos-0.3.0.dist-info/entry_points.txt
torch_nos-0.3.0.dist-info/top_level.txt
torch_nos-0.3.0.dist-info/RECORD
