Metadata-Version: 2.1
Name: torch-nos
Version: 0.3.0
Summary: Nitrous Oxide for your AI Infrastructure.
License: Apache License
Project-URL: Documentation, https://docs.nos.run/
Project-URL: Source Code, https://github.com/autonomi-ai/nos
Project-URL: Homepage, https://nos.run/
Classifier: Development Status :: 4 - Beta
Classifier: Programming Language :: Python
Classifier: Environment :: Console
Classifier: Environment :: GPU
Classifier: Intended Audience :: Developers
Classifier: Intended Audience :: Education
Classifier: Intended Audience :: Information Technology
Classifier: Intended Audience :: Science/Research
Classifier: Topic :: Software Development :: Libraries
Classifier: Topic :: Scientific/Engineering :: Artificial Intelligence
Classifier: Topic :: Scientific/Engineering :: Image Processing
Classifier: License :: OSI Approved :: MIT License
Classifier: Programming Language :: Python :: 3 :: Only
Classifier: Programming Language :: Python :: 3.10
Classifier: Programming Language :: Python :: 3.11
Requires-Python: >=3.10
License-File: LICENSE
Requires-Dist: agi-pack >=0.2.0
Requires-Dist: cloudpickle >=2.2.1
Requires-Dist: docker >=6.0.0
Requires-Dist: filelock
Requires-Dist: gitpython
Requires-Dist: grpcio-tools <=1.49.1
Requires-Dist: humanize
Requires-Dist: loguru >=0.7.0
Requires-Dist: opencv-python-headless >=4.6.0.66
Requires-Dist: pandas
Requires-Dist: Pillow
Requires-Dist: psutil >=5.9.5
Requires-Dist: py-cpuinfo >=9.0.0
Requires-Dist: pydantic >=2.5.0
Requires-Dist: python-multipart
Requires-Dist: pyyaml
Requires-Dist: rich >=12.5.1
Requires-Dist: sentry-sdk[loguru]
Requires-Dist: tqdm
Requires-Dist: typer >=0.7.0
Requires-Dist: typing-extensions >=4.5.0
Provides-Extra: all
Requires-Dist: diffusers >=0.17.1 ; extra == 'all'
Requires-Dist: huggingface-hub >=0.17.3 ; extra == 'all'
Requires-Dist: pyarrow >=12.0.0 ; extra == 'all'
Requires-Dist: ray[default] >=2.9.1 ; extra == 'all'
Requires-Dist: safetensors >=0.3.0 ; extra == 'all'
Requires-Dist: tabulate ; extra == 'all'
Requires-Dist: timm >=0.9.2 ; extra == 'all'
Requires-Dist: transformers >=4.35.0 ; extra == 'all'
Requires-Dist: torch >=2.0.1 ; extra == 'all'
Requires-Dist: torchaudio ; extra == 'all'
Requires-Dist: torchvision ; extra == 'all'
Requires-Dist: fastapi ; extra == 'all'
Requires-Dist: uvicorn[standard] ; extra == 'all'
Provides-Extra: cpu
Provides-Extra: dev
Requires-Dist: black[jupyter] ==22.3.0 ; extra == 'dev'
Requires-Dist: build ==0.10.0 ; extra == 'dev'
Requires-Dist: build ; extra == 'dev'
Requires-Dist: memray ; extra == 'dev'
Requires-Dist: pre-commit ==3.2.2 ; extra == 'dev'
Requires-Dist: ruff ==0.0.262 ; extra == 'dev'
Requires-Dist: twine ; extra == 'dev'
Provides-Extra: docs
Requires-Dist: mkdocs >=1.5.2 ; extra == 'docs'
Requires-Dist: mkdocs-blog-plugin ; extra == 'docs'
Requires-Dist: mkdocs-exclude ; extra == 'docs'
Requires-Dist: mkdocs-include-markdown-plugin ; extra == 'docs'
Requires-Dist: mkdocs-material-extensions >=1.2 ; extra == 'docs'
Requires-Dist: mkdocs-material[imaging] >=9.5.0 ; extra == 'docs'
Requires-Dist: mkdocs-pymdownx-material-extras ; extra == 'docs'
Requires-Dist: mkdocs-same-dir ; extra == 'docs'
Requires-Dist: mkdocs-table-reader-plugin ; extra == 'docs'
Requires-Dist: mkdocs-typer ; extra == 'docs'
Requires-Dist: mkdocstrings ; extra == 'docs'
Requires-Dist: mkdocstrings-python ; extra == 'docs'
Requires-Dist: mkdocstrings[python] ; extra == 'docs'
Provides-Extra: gpu
Provides-Extra: http
Requires-Dist: fastapi ; extra == 'http'
Requires-Dist: uvicorn[standard] ; extra == 'http'
Provides-Extra: server
Requires-Dist: diffusers >=0.17.1 ; extra == 'server'
Requires-Dist: huggingface-hub >=0.17.3 ; extra == 'server'
Requires-Dist: pyarrow >=12.0.0 ; extra == 'server'
Requires-Dist: ray[default] >=2.9.1 ; extra == 'server'
Requires-Dist: safetensors >=0.3.0 ; extra == 'server'
Requires-Dist: tabulate ; extra == 'server'
Requires-Dist: timm >=0.9.2 ; extra == 'server'
Requires-Dist: transformers >=4.35.0 ; extra == 'server'
Requires-Dist: torch >=2.0.1 ; extra == 'server'
Requires-Dist: torchaudio ; extra == 'server'
Requires-Dist: torchvision ; extra == 'server'
Provides-Extra: test
Requires-Dist: httpx ; extra == 'test'
Requires-Dist: pytest ; extra == 'test'
Requires-Dist: pytest-asyncio ; extra == 'test'
Requires-Dist: typeguard ; extra == 'test'
